uni/common/__init__.py
uni/common/exit_code.py
uni/common/logger.py
uni/common/main.py
uni/common/core/__init__.py
uni/common/core/common.py
uni/common/core/connectivity_map.py
uni/common/core/node_history.py
uni/common/core/uid_generator.py
uni/common/core/error/__init__.py
uni/common/core/error/defs.py
uni/common/core/error/util.py
uni/common/core/multigraph/__init__.py
uni/common/core/multigraph/edge.py
uni/common/core/multigraph/graph.py
uni/common/core/multigraph/node_graph_api.py
uni/common/core/multigraph/typing.py
uni/common/core/nnir_graph/__init__.py
uni/common/core/nnir_graph/nnir_edge.py
uni/common/core/nnir_graph/nnir_graph.py
uni/common/core/nnir_graph/semantics.py
uni/common/core/nnir_graph/nnir_nodes/__init__.py
uni/common/core/nnir_graph/nnir_nodes/abs.py
uni/common/core/nnir_graph/nnir_nodes/add.py
uni/common/core/nnir_graph/nnir_nodes/argmax.py
uni/common/core/nnir_graph/nnir_nodes/average_pool2d.py
uni/common/core/nnir_graph/nnir_nodes/batch_norm.py
uni/common/core/nnir_graph/nnir_nodes/binary_op.py
uni/common/core/nnir_graph/nnir_nodes/box_decode.py
uni/common/core/nnir_graph/nnir_nodes/broadcast.py
uni/common/core/nnir_graph/nnir_nodes/common.py
uni/common/core/nnir_graph/nnir_nodes/concat.py
uni/common/core/nnir_graph/nnir_nodes/conv2d.py
uni/common/core/nnir_graph/nnir_nodes/conv2dtranspose.py
uni/common/core/nnir_graph/nnir_nodes/cos.py
uni/common/core/nnir_graph/nnir_nodes/div.py
uni/common/core/nnir_graph/nnir_nodes/dummy_node.py
uni/common/core/nnir_graph/nnir_nodes/equal.py
uni/common/core/nnir_graph/nnir_nodes/exp.py
uni/common/core/nnir_graph/nnir_nodes/expand_dims.py
uni/common/core/nnir_graph/nnir_nodes/fully_connected.py
uni/common/core/nnir_graph/nnir_nodes/gelu.py
uni/common/core/nnir_graph/nnir_nodes/group_norm.py
uni/common/core/nnir_graph/nnir_nodes/hard_sigmoid.py
uni/common/core/nnir_graph/nnir_nodes/hard_swish.py
uni/common/core/nnir_graph/nnir_nodes/identity.py
uni/common/core/nnir_graph/nnir_nodes/instance_norm.py
uni_pytorch-3.17.1.dist-info/METADATA
uni_pytorch-3.17.1.dist-info/WHEEL
uni_pytorch-3.17.1.dist-info/entry_points.txt
uni_pytorch-3.17.1.dist-info/top_level.txt
uni_pytorch-3.17.1.dist-info/RECORD
