Metadata-Version: 2.4
Name: uni_pytorch
Version: 3.17.1
Summary: PyTorch to uni-model converter
Author: ssi-dnn-dev
Author-email: ssi-dnn-dev@sony.com
Maintainer: ssi-dnn-dev
Maintainer-email: ssi-dnn-dev@sony.com
Requires-Python: >=3.9, <3.13
Requires-Dist: uni-model==10.0.23
Requires-Dist: networkx~=3.0.0
Requires-Dist: mct-quantizers~=1.6.0
Requires-Dist: packaging
Requires-Dist: edge-mdt-cl~=1.0.0
Requires-Dist: numpy
Requires-Dist: onnx~=1.16.0; python_version < "3.10"
Requires-Dist: onnx~=1.17.0; python_version >= "3.10"
Requires-Dist: onnxruntime~=1.19.2; python_version < "3.10"
Requires-Dist: onnxruntime~=1.21.0; python_version >= "3.10"
Requires-Dist: onnxruntime-extensions~=0.13.0
Dynamic: author
Dynamic: author-email
Dynamic: maintainer
Dynamic: maintainer-email
Dynamic: requires-dist
Dynamic: requires-python
Dynamic: summary
